takion_tls/__init__.py
takion_tls/__version__.py
takion_tls/exceptions.py
takion_tls/sessions.py
takion_tls/c/__init__.py
takion_tls/c/cffi.py
takion_tls/models/__init__.py
takion_tls/models/clients.py
takion_tls/models/cookies.py
takion_tls/models/response.py
takion_tls/models/structures.py
takion_tls-0.1.0.dist-info/LICENSE
takion_tls-0.1.0.dist-info/METADATA
takion_tls-0.1.0.dist-info/WHEEL
takion_tls-0.1.0.dist-info/top_level.txt
takion_tls-0.1.0.dist-info/RECORD
