Metadata-Version: 2.1
Name: takion-tls
Version: 0.1.0
Summary: A Python TLS client for auto-updating, customizable secure connections, ideal for advanced web scraping and reverse engineering. By TakionAPI
Home-page: https://github.com/Takion-API-Services/takion-tls
Author: GlizzyKingDreko
Author-email: glizzykingdreko@protonmail.com
Project-URL: Documentation, https://github.com/Takion-API-Services/takion-tls
Project-URL: Source, https://github.com/Takion-API-Services/takion-tls
Project-URL: Tracker, https://github.com/Takion-API-Services/takion-tls/issues
Keywords: tls client,web scraping,reverse engineering,takion api
Classifier: Development Status :: 3 - Alpha
Classifier: Intended Audience :: Developers
Classifier: Topic :: Software Development :: Build Tools
Classifier: License :: OSI Approved :: MIT License
Classifier: Programming Language :: Python :: 3
Classifier: Programming Language :: Python :: 3.11
Classifier: Operating System :: OS Independent
Requires-Python: >=3.11
License-File: LICENSE
Requires-Dist: asyncio ==3.4.3
Requires-Dist: certifi ==2024.2.2
Requires-Dist: charset-normalizer ==3.3.2
Requires-Dist: colorama ==0.4.6
Requires-Dist: idna ==3.7
Requires-Dist: requests ==2.31.0
Requires-Dist: resilient-caller ==0.2.2
Requires-Dist: tasks-logger ==0.1.0
Requires-Dist: urllib3 ==2.2.1
